{ "columns":21,
 "image":"A4_\u5c55\u5f00_5\u5c42_\u56fe\u50cf\u8f93\u51fa.png",
 "imageheight":1008,
 "imagewidth":1008,
 "margin":0,
 "name":"A4_\u5c4b\u9876_\u5730\u5f62",
 "spacing":0,
 "tilecount":441,
 "tiledversion":"1.9.2",
 "tileheight":48,
 "tilewidth":48,
 "type":"tileset",
 "version":"1.9",
 "wangsets":[
        {
         "colors":[
                {
                 "color":"#ff0000",
                 "name":"",
                 "probability":1,
                 "tile":66
                }],
         "name":"0_0_0",
         "tile":66,
         "type":"mixed",
         "wangtiles":[
                {
                 "tileid":0,
                 "wangid":[0, 0, 1, 1, 1, 0, 0, 0]
                }, 
                {
                 "tileid":1,
                 "wangid":[0, 0, 1, 1, 1, 1, 1, 0]
                }, 
                {
                 "tileid":2,
                 "wangid":[0, 0, 0, 0, 1, 1, 1, 0]
                }, 
                {
                 "tileid":3,
                 "wangid":[0, 0, 0, 0, 1, 0, 0, 0]
                }, 
                {
                 "tileid":4,
                 "wangid":[1, 1, 1, 0, 1, 1, 1, 1]
                }, 
                {
                 "tileid":5,
                 "wangid":[1, 1, 1, 0, 1, 0, 1, 1]
                }, 
                {
                 "tileid":6,
                 "wangid":[1, 1, 1, 1, 1, 0, 1, 1]
                }, 
                {
                 "tileid":21,
                 "wangid":[1, 1, 1, 1, 1, 0, 0, 0]
                }, 
                {
                 "tileid":22,
                 "wangid":[1, 1, 1, 1, 1, 1, 1, 1]
                }, 
                {
                 "tileid":23,
                 "wangid":[1, 0, 0, 0, 1, 1, 1, 1]
                }, 
                {
                 "tileid":24,
                 "wangid":[1, 0, 0, 0, 1, 0, 0, 0]
                }, 
                {
                 "tileid":25,
                 "wangid":[1, 0, 1, 0, 1, 1, 1, 1]
                }, 
                {
                 "tileid":26,
                 "wangid":[1, 0, 1, 0, 1, 0, 1, 0]
                }, 
                {
                 "tileid":27,
                 "wangid":[1, 1, 1, 1, 1, 0, 1, 0]
                }, 
                {
                 "tileid":42,
                 "wangid":[1, 1, 1, 0, 0, 0, 0, 0]
                }, 
                {
                 "tileid":43,
                 "wangid":[1, 1, 1, 0, 0, 0, 1, 1]
                }, 
                {
                 "tileid":44,
                 "wangid":[1, 0, 0, 0, 0, 0, 1, 1]
                }, 
                {
                 "tileid":45,
                 "wangid":[1, 0, 0, 0, 0, 0, 0, 0]
                }, 
                {
                 "tileid":46,
                 "wangid":[1, 0, 1, 1, 1, 1, 1, 1]
                }, 
                {
                 "tileid":47,
                 "wangid":[1, 0, 1, 1, 1, 1, 1, 0]
                }, 
                {
                 "tileid":48,
                 "wangid":[1, 1, 1, 1, 1, 1, 1, 0]
                }, 
                {
                 "tileid":63,
                 "wangid":[0, 0, 1, 0, 0, 0, 0, 0]
                }, 
                {
                 "tileid":64,
                 "wangid":[0, 0, 1, 0, 0, 0, 1, 0]
                }, 
                {
                 "tileid":65,
                 "wangid":[0, 0, 0, 0, 0, 0, 1, 0]
                }, 
                {
                 "tileid":67,
                 "wangid":[0, 0, 1, 0, 1, 1, 1, 0]
                }, 
                {
                 "tileid":68,
                 "wangid":[0, 0, 1, 0, 1, 0, 1, 0]
                }, 
                {
                 "tileid":69,
                 "wangid":[0, 0, 1, 1, 1, 0, 1, 0]
                }, 
                {
                 "tileid":84,
                 "wangid":[1, 1, 1, 0, 1, 0, 0, 0]
                }, 
                {
                 "tileid":85,
                 "wangid":[1, 0, 0, 0, 1, 0, 1, 1]
                }, 
                {
                 "tileid":86,
                 "wangid":[1, 1, 1, 0, 1, 1, 1, 0]
                }, 
                {
                 "tileid":87,
                 "wangid":[1, 0, 1, 1, 1, 0, 1, 1]
                }, 
                {
                 "tileid":88,
                 "wangid":[1, 0, 1, 0, 0, 0, 1, 1]
                }, 
                {
                 "tileid":89,
                 "wangid":[1, 0, 1, 0, 0, 0, 1, 0]
                }, 
                {
                 "tileid":90,
                 "wangid":[1, 1, 1, 0, 0, 0, 1, 0]
                }, 
                {
                 "tileid":105,
                 "wangid":[1, 0, 1, 0, 1, 0, 0, 0]
                }, 
                {
                 "tileid":106,
                 "wangid":[1, 0, 0, 0, 1, 0, 1, 0]
                }, 
                {
                 "tileid":107,
                 "wangid":[0, 0, 1, 0, 1, 0, 0, 0]
                }, 
                {
                 "tileid":108,
                 "wangid":[0, 0, 0, 0, 1, 0, 1, 0]
                }, 
                {
                 "tileid":109,
                 "wangid":[1, 0, 1, 0, 1, 0, 1, 1]
                }, 
                {
                 "tileid":110,
                 "wangid":[1, 1, 1, 0, 1, 0, 1, 0]
                }, 
                {
                 "tileid":126,
                 "wangid":[1, 0, 1, 1, 1, 0, 0, 0]
                }, 
                {
                 "tileid":127,
                 "wangid":[1, 0, 0, 0, 1, 1, 1, 0]
                }, 
                {
                 "tileid":128,
                 "wangid":[1, 0, 1, 0, 0, 0, 0, 0]
                }, 
                {
                 "tileid":129,
                 "wangid":[1, 0, 0, 0, 0, 0, 1, 0]
                }, 
                {
                 "tileid":130,
                 "wangid":[1, 0, 1, 0, 1, 1, 1, 0]
                }, 
                {
                 "tileid":131,
                 "wangid":[1, 0, 1, 1, 1, 0, 1, 0]
                }]
        }, 
        {
         "colors":[
                {
                 "color":"#ff0000",
                 "name":"",
                 "probability":1,
                 "tile":73
                }],
         "name":"0_1_0",
         "tile":73,
         "type":"mixed",
         "wangtiles":[
                {
                 "tileid":7,
                 "wangid":[0, 0, 1, 1, 1, 0, 0, 0]
                }, 
                {
                 "tileid":8,
                 "wangid":[0, 0, 1, 1, 1, 1, 1, 0]
                }, 
                {
                 "tileid":9,
                 "wangid":[0, 0, 0, 0, 1, 1, 1, 0]
                }, 
                {
                 "tileid":10,
                 "wangid":[0, 0, 0, 0, 1, 0, 0, 0]
                }, 
                {
                 "tileid":11,
                 "wangid":[1, 1, 1, 0, 1, 1, 1, 1]
                }, 
                {
                 "tileid":12,
                 "wangid":[1, 1, 1, 0, 1, 0, 1, 1]
                }, 
                {
                 "tileid":13,
                 "wangid":[1, 1, 1, 1, 1, 0, 1, 1]
                }, 
                {
                 "tileid":28,
                 "wangid":[1, 1, 1, 1, 1, 0, 0, 0]
                }, 
                {
                 "tileid":29,
                 "wangid":[1, 1, 1, 1, 1, 1, 1, 1]
                }, 
                {
                 "tileid":30,
                 "wangid":[1, 0, 0, 0, 1, 1, 1, 1]
                }, 
                {
                 "tileid":31,
                 "wangid":[1, 0, 0, 0, 1, 0, 0, 0]
                }, 
                {
                 "tileid":32,
                 "wangid":[1, 0, 1, 0, 1, 1, 1, 1]
                }, 
                {
                 "tileid":33,
                 "wangid":[1, 0, 1, 0, 1, 0, 1, 0]
                }, 
                {
                 "tileid":34,
                 "wangid":[1, 1, 1, 1, 1, 0, 1, 0]
                }, 
                {
                 "tileid":49,
                 "wangid":[1, 1, 1, 0, 0, 0, 0, 0]
                }, 
                {
                 "tileid":50,
                 "wangid":[1, 1, 1, 0, 0, 0, 1, 1]
                }, 
                {
                 "tileid":51,
                 "wangid":[1, 0, 0, 0, 0, 0, 1, 1]
                }, 
                {
                 "tileid":52,
                 "wangid":[1, 0, 0, 0, 0, 0, 0, 0]
                }, 
                {
                 "tileid":53,
                 "wangid":[1, 0, 1, 1, 1, 1, 1, 1]
                }, 
                {
                 "tileid":54,
                 "wangid":[1, 0, 1, 1, 1, 1, 1, 0]
                }, 
                {
                 "tileid":55,
                 "wangid":[1, 1, 1, 1, 1, 1, 1, 0]
                }, 
                {
                 "tileid":70,
                 "wangid":[0, 0, 1, 0, 0, 0, 0, 0]
                }, 
                {
                 "tileid":71,
                 "wangid":[0, 0, 1, 0, 0, 0, 1, 0]
                }, 
                {
                 "tileid":72,
                 "wangid":[0, 0, 0, 0, 0, 0, 1, 0]
                }, 
                {
                 "tileid":74,
                 "wangid":[0, 0, 1, 0, 1, 1, 1, 0]
                }, 
                {
                 "tileid":75,
                 "wangid":[0, 0, 1, 0, 1, 0, 1, 0]
                }, 
                {
                 "tileid":76,
                 "wangid":[0, 0, 1, 1, 1, 0, 1, 0]
                }, 
                {
                 "tileid":91,
                 "wangid":[1, 1, 1, 0, 1, 0, 0, 0]
                }, 
                {
                 "tileid":92,
                 "wangid":[1, 0, 0, 0, 1, 0, 1, 1]
                }, 
                {
                 "tileid":93,
                 "wangid":[1, 1, 1, 0, 1, 1, 1, 0]
                }, 
                {
                 "tileid":94,
                 "wangid":[1, 0, 1, 1, 1, 0, 1, 1]
                }, 
                {
                 "tileid":95,
                 "wangid":[1, 0, 1, 0, 0, 0, 1, 1]
                }, 
                {
                 "tileid":96,
                 "wangid":[1, 0, 1, 0, 0, 0, 1, 0]
                }, 
                {
                 "tileid":97,
                 "wangid":[1, 1, 1, 0, 0, 0, 1, 0]
                }, 
                {
                 "tileid":112,
                 "wangid":[1, 0, 1, 0, 1, 0, 0, 0]
                }, 
                {
                 "tileid":113,
                 "wangid":[1, 0, 0, 0, 1, 0, 1, 0]
                }, 
                {
                 "tileid":114,
                 "wangid":[0, 0, 1, 0, 1, 0, 0, 0]
                }, 
                {
                 "tileid":115,
                 "wangid":[0, 0, 0, 0, 1, 0, 1, 0]
                }, 
                {
                 "tileid":116,
                 "wangid":[1, 0, 1, 0, 1, 0, 1, 1]
                }, 
                {
                 "tileid":117,
                 "wangid":[1, 1, 1, 0, 1, 0, 1, 0]
                }, 
                {
                 "tileid":133,
                 "wangid":[1, 0, 1, 1, 1, 0, 0, 0]
                }, 
                {
                 "tileid":134,
                 "wangid":[1, 0, 0, 0, 1, 1, 1, 0]
                }, 
                {
                 "tileid":135,
                 "wangid":[1, 0, 1, 0, 0, 0, 0, 0]
                }, 
                {
                 "tileid":136,
                 "wangid":[1, 0, 0, 0, 0, 0, 1, 0]
                }, 
                {
                 "tileid":137,
                 "wangid":[1, 0, 1, 0, 1, 1, 1, 0]
                }, 
                {
                 "tileid":138,
                 "wangid":[1, 0, 1, 1, 1, 0, 1, 0]
                }]
        }, 
        {
         "colors":[
                {
                 "color":"#ff0000",
                 "name":"",
                 "probability":1,
                 "tile":80
                }],
         "name":"0_2_0",
         "tile":80,
         "type":"mixed",
         "wangtiles":[
                {
                 "tileid":14,
                 "wangid":[0, 0, 1, 1, 1, 0, 0, 0]
                }, 
                {
                 "tileid":15,
                 "wangid":[0, 0, 1, 1, 1, 1, 1, 0]
                }, 
                {
                 "tileid":16,
                 "wangid":[0, 0, 0, 0, 1, 1, 1, 0]
                }, 
                {
                 "tileid":17,
                 "wangid":[0, 0, 0, 0, 1, 0, 0, 0]
                }, 
                {
                 "tileid":18,
                 "wangid":[1, 1, 1, 0, 1, 1, 1, 1]
                }, 
                {
                 "tileid":19,
                 "wangid":[1, 1, 1, 0, 1, 0, 1, 1]
                }, 
                {
                 "tileid":20,
                 "wangid":[1, 1, 1, 1, 1, 0, 1, 1]
                }, 
                {
                 "tileid":35,
                 "wangid":[1, 1, 1, 1, 1, 0, 0, 0]
                }, 
                {
                 "tileid":36,
                 "wangid":[1, 1, 1, 1, 1, 1, 1, 1]
                }, 
                {
                 "tileid":37,
                 "wangid":[1, 0, 0, 0, 1, 1, 1, 1]
                }, 
                {
                 "tileid":38,
                 "wangid":[1, 0, 0, 0, 1, 0, 0, 0]
                }, 
                {
                 "tileid":39,
                 "wangid":[1, 0, 1, 0, 1, 1, 1, 1]
                }, 
                {
                 "tileid":40,
                 "wangid":[1, 0, 1, 0, 1, 0, 1, 0]
                }, 
                {
                 "tileid":41,
                 "wangid":[1, 1, 1, 1, 1, 0, 1, 0]
                }, 
                {
                 "tileid":56,
                 "wangid":[1, 1, 1, 0, 0, 0, 0, 0]
                }, 
                {
                 "tileid":57,
                 "wangid":[1, 1, 1, 0, 0, 0, 1, 1]
                }, 
                {
                 "tileid":58,
                 "wangid":[1, 0, 0, 0, 0, 0, 1, 1]
                }, 
                {
                 "tileid":59,
                 "wangid":[1, 0, 0, 0, 0, 0, 0, 0]
                }, 
                {
                 "tileid":60,
                 "wangid":[1, 0, 1, 1, 1, 1, 1, 1]
                }, 
                {
                 "tileid":61,
                 "wangid":[1, 0, 1, 1, 1, 1, 1, 0]
                }, 
                {
                 "tileid":62,
                 "wangid":[1, 1, 1, 1, 1, 1, 1, 0]
                }, 
                {
                 "tileid":77,
                 "wangid":[0, 0, 1, 0, 0, 0, 0, 0]
                }, 
                {
                 "tileid":78,
                 "wangid":[0, 0, 1, 0, 0, 0, 1, 0]
                }, 
                {
                 "tileid":79,
                 "wangid":[0, 0, 0, 0, 0, 0, 1, 0]
                }, 
                {
                 "tileid":81,
                 "wangid":[0, 0, 1, 0, 1, 1, 1, 0]
                }, 
                {
                 "tileid":82,
                 "wangid":[0, 0, 1, 0, 1, 0, 1, 0]
                }, 
                {
                 "tileid":83,
                 "wangid":[0, 0, 1, 1, 1, 0, 1, 0]
                }, 
                {
                 "tileid":98,
                 "wangid":[1, 1, 1, 0, 1, 0, 0, 0]
                }, 
                {
                 "tileid":99,
                 "wangid":[1, 0, 0, 0, 1, 0, 1, 1]
                }, 
                {
                 "tileid":100,
                 "wangid":[1, 1, 1, 0, 1, 1, 1, 0]
                }, 
                {
                 "tileid":101,
                 "wangid":[1, 0, 1, 1, 1, 0, 1, 1]
                }, 
                {
                 "tileid":102,
                 "wangid":[1, 0, 1, 0, 0, 0, 1, 1]
                }, 
                {
                 "tileid":103,
                 "wangid":[1, 0, 1, 0, 0, 0, 1, 0]
                }, 
                {
                 "tileid":104,
                 "wangid":[1, 1, 1, 0, 0, 0, 1, 0]
                }, 
                {
                 "tileid":119,
                 "wangid":[1, 0, 1, 0, 1, 0, 0, 0]
                }, 
                {
                 "tileid":120,
                 "wangid":[1, 0, 0, 0, 1, 0, 1, 0]
                }, 
                {
                 "tileid":121,
                 "wangid":[0, 0, 1, 0, 1, 0, 0, 0]
                }, 
                {
                 "tileid":122,
                 "wangid":[0, 0, 0, 0, 1, 0, 1, 0]
                }, 
                {
                 "tileid":123,
                 "wangid":[1, 0, 1, 0, 1, 0, 1, 1]
                }, 
                {
                 "tileid":124,
                 "wangid":[1, 1, 1, 0, 1, 0, 1, 0]
                }, 
                {
                 "tileid":140,
                 "wangid":[1, 0, 1, 1, 1, 0, 0, 0]
                }, 
                {
                 "tileid":141,
                 "wangid":[1, 0, 0, 0, 1, 1, 1, 0]
                }, 
                {
                 "tileid":142,
                 "wangid":[1, 0, 1, 0, 0, 0, 0, 0]
                }, 
                {
                 "tileid":143,
                 "wangid":[1, 0, 0, 0, 0, 0, 1, 0]
                }, 
                {
                 "tileid":144,
                 "wangid":[1, 0, 1, 0, 1, 1, 1, 0]
                }, 
                {
                 "tileid":145,
                 "wangid":[1, 0, 1, 1, 1, 0, 1, 0]
                }]
        }, 
        {
         "colors":[
                {
                 "color":"#ff0000",
                 "name":"",
                 "probability":1,
                 "tile":213
                }],
         "name":"0_0_1",
         "tile":213,
         "type":"mixed",
         "wangtiles":[
                {
                 "tileid":147,
                 "wangid":[0, 0, 1, 1, 1, 0, 0, 0]
                }, 
                {
                 "tileid":148,
                 "wangid":[0, 0, 1, 1, 1, 1, 1, 0]
                }, 
                {
                 "tileid":149,
                 "wangid":[0, 0, 0, 0, 1, 1, 1, 0]
                }, 
                {
                 "tileid":150,
                 "wangid":[0, 0, 0, 0, 1, 0, 0, 0]
                }, 
                {
                 "tileid":151,
                 "wangid":[1, 1, 1, 0, 1, 1, 1, 1]
                }, 
                {
                 "tileid":152,
                 "wangid":[1, 1, 1, 0, 1, 0, 1, 1]
                }, 
                {
                 "tileid":153,
                 "wangid":[1, 1, 1, 1, 1, 0, 1, 1]
                }, 
                {
                 "tileid":168,
                 "wangid":[1, 1, 1, 1, 1, 0, 0, 0]
                }, 
                {
                 "tileid":169,
                 "wangid":[1, 1, 1, 1, 1, 1, 1, 1]
                }, 
                {
                 "tileid":170,
                 "wangid":[1, 0, 0, 0, 1, 1, 1, 1]
                }, 
                {
                 "tileid":171,
                 "wangid":[1, 0, 0, 0, 1, 0, 0, 0]
                }, 
                {
                 "tileid":172,
                 "wangid":[1, 0, 1, 0, 1, 1, 1, 1]
                }, 
                {
                 "tileid":173,
                 "wangid":[1, 0, 1, 0, 1, 0, 1, 0]
                }, 
                {
                 "tileid":174,
                 "wangid":[1, 1, 1, 1, 1, 0, 1, 0]
                }, 
                {
                 "tileid":189,
                 "wangid":[1, 1, 1, 0, 0, 0, 0, 0]
                }, 
                {
                 "tileid":190,
                 "wangid":[1, 1, 1, 0, 0, 0, 1, 1]
                }, 
                {
                 "tileid":191,
                 "wangid":[1, 0, 0, 0, 0, 0, 1, 1]
                }, 
                {
                 "tileid":192,
                 "wangid":[1, 0, 0, 0, 0, 0, 0, 0]
                }, 
                {
                 "tileid":193,
                 "wangid":[1, 0, 1, 1, 1, 1, 1, 1]
                }, 
                {
                 "tileid":194,
                 "wangid":[1, 0, 1, 1, 1, 1, 1, 0]
                }, 
                {
                 "tileid":195,
                 "wangid":[1, 1, 1, 1, 1, 1, 1, 0]
                }, 
                {
                 "tileid":210,
                 "wangid":[0, 0, 1, 0, 0, 0, 0, 0]
                }, 
                {
                 "tileid":211,
                 "wangid":[0, 0, 1, 0, 0, 0, 1, 0]
                }, 
                {
                 "tileid":212,
                 "wangid":[0, 0, 0, 0, 0, 0, 1, 0]
                }, 
                {
                 "tileid":214,
                 "wangid":[0, 0, 1, 0, 1, 1, 1, 0]
                }, 
                {
                 "tileid":215,
                 "wangid":[0, 0, 1, 0, 1, 0, 1, 0]
                }, 
                {
                 "tileid":216,
                 "wangid":[0, 0, 1, 1, 1, 0, 1, 0]
                }, 
                {
                 "tileid":231,
                 "wangid":[1, 1, 1, 0, 1, 0, 0, 0]
                }, 
                {
                 "tileid":232,
                 "wangid":[1, 0, 0, 0, 1, 0, 1, 1]
                }, 
                {
                 "tileid":233,
                 "wangid":[1, 1, 1, 0, 1, 1, 1, 0]
                }, 
                {
                 "tileid":234,
                 "wangid":[1, 0, 1, 1, 1, 0, 1, 1]
                }, 
                {
                 "tileid":235,
                 "wangid":[1, 0, 1, 0, 0, 0, 1, 1]
                }, 
                {
                 "tileid":236,
                 "wangid":[1, 0, 1, 0, 0, 0, 1, 0]
                }, 
                {
                 "tileid":237,
                 "wangid":[1, 1, 1, 0, 0, 0, 1, 0]
                }, 
                {
                 "tileid":252,
                 "wangid":[1, 0, 1, 0, 1, 0, 0, 0]
                }, 
                {
                 "tileid":253,
                 "wangid":[1, 0, 0, 0, 1, 0, 1, 0]
                }, 
                {
                 "tileid":254,
                 "wangid":[0, 0, 1, 0, 1, 0, 0, 0]
                }, 
                {
                 "tileid":255,
                 "wangid":[0, 0, 0, 0, 1, 0, 1, 0]
                }, 
                {
                 "tileid":256,
                 "wangid":[1, 0, 1, 0, 1, 0, 1, 1]
                }, 
                {
                 "tileid":257,
                 "wangid":[1, 1, 1, 0, 1, 0, 1, 0]
                }, 
                {
                 "tileid":273,
                 "wangid":[1, 0, 1, 1, 1, 0, 0, 0]
                }, 
                {
                 "tileid":274,
                 "wangid":[1, 0, 0, 0, 1, 1, 1, 0]
                }, 
                {
                 "tileid":275,
                 "wangid":[1, 0, 1, 0, 0, 0, 0, 0]
                }, 
                {
                 "tileid":276,
                 "wangid":[1, 0, 0, 0, 0, 0, 1, 0]
                }, 
                {
                 "tileid":277,
                 "wangid":[1, 0, 1, 0, 1, 1, 1, 0]
                }, 
                {
                 "tileid":278,
                 "wangid":[1, 0, 1, 1, 1, 0, 1, 0]
                }]
        }, 
        {
         "colors":[
                {
                 "color":"#ff0000",
                 "name":"",
                 "probability":1,
                 "tile":220
                }],
         "name":"0_1_1",
         "tile":220,
         "type":"mixed",
         "wangtiles":[
                {
                 "tileid":154,
                 "wangid":[0, 0, 1, 1, 1, 0, 0, 0]
                }, 
                {
                 "tileid":155,
                 "wangid":[0, 0, 1, 1, 1, 1, 1, 0]
                }, 
                {
                 "tileid":156,
                 "wangid":[0, 0, 0, 0, 1, 1, 1, 0]
                }, 
                {
                 "tileid":157,
                 "wangid":[0, 0, 0, 0, 1, 0, 0, 0]
                }, 
                {
                 "tileid":158,
                 "wangid":[1, 1, 1, 0, 1, 1, 1, 1]
                }, 
                {
                 "tileid":159,
                 "wangid":[1, 1, 1, 0, 1, 0, 1, 1]
                }, 
                {
                 "tileid":160,
                 "wangid":[1, 1, 1, 1, 1, 0, 1, 1]
                }, 
                {
                 "tileid":175,
                 "wangid":[1, 1, 1, 1, 1, 0, 0, 0]
                }, 
                {
                 "tileid":176,
                 "wangid":[1, 1, 1, 1, 1, 1, 1, 1]
                }, 
                {
                 "tileid":177,
                 "wangid":[1, 0, 0, 0, 1, 1, 1, 1]
                }, 
                {
                 "tileid":178,
                 "wangid":[1, 0, 0, 0, 1, 0, 0, 0]
                }, 
                {
                 "tileid":179,
                 "wangid":[1, 0, 1, 0, 1, 1, 1, 1]
                }, 
                {
                 "tileid":180,
                 "wangid":[1, 0, 1, 0, 1, 0, 1, 0]
                }, 
                {
                 "tileid":181,
                 "wangid":[1, 1, 1, 1, 1, 0, 1, 0]
                }, 
                {
                 "tileid":196,
                 "wangid":[1, 1, 1, 0, 0, 0, 0, 0]
                }, 
                {
                 "tileid":197,
                 "wangid":[1, 1, 1, 0, 0, 0, 1, 1]
                }, 
                {
                 "tileid":198,
                 "wangid":[1, 0, 0, 0, 0, 0, 1, 1]
                }, 
                {
                 "tileid":199,
                 "wangid":[1, 0, 0, 0, 0, 0, 0, 0]
                }, 
                {
                 "tileid":200,
                 "wangid":[1, 0, 1, 1, 1, 1, 1, 1]
                }, 
                {
                 "tileid":201,
                 "wangid":[1, 0, 1, 1, 1, 1, 1, 0]
                }, 
                {
                 "tileid":202,
                 "wangid":[1, 1, 1, 1, 1, 1, 1, 0]
                }, 
                {
                 "tileid":217,
                 "wangid":[0, 0, 1, 0, 0, 0, 0, 0]
                }, 
                {
                 "tileid":218,
                 "wangid":[0, 0, 1, 0, 0, 0, 1, 0]
                }, 
                {
                 "tileid":219,
                 "wangid":[0, 0, 0, 0, 0, 0, 1, 0]
                }, 
                {
                 "tileid":221,
                 "wangid":[0, 0, 1, 0, 1, 1, 1, 0]
                }, 
                {
                 "tileid":222,
                 "wangid":[0, 0, 1, 0, 1, 0, 1, 0]
                }, 
                {
                 "tileid":223,
                 "wangid":[0, 0, 1, 1, 1, 0, 1, 0]
                }, 
                {
                 "tileid":238,
                 "wangid":[1, 1, 1, 0, 1, 0, 0, 0]
                }, 
                {
                 "tileid":239,
                 "wangid":[1, 0, 0, 0, 1, 0, 1, 1]
                }, 
                {
                 "tileid":240,
                 "wangid":[1, 1, 1, 0, 1, 1, 1, 0]
                }, 
                {
                 "tileid":241,
                 "wangid":[1, 0, 1, 1, 1, 0, 1, 1]
                }, 
                {
                 "tileid":242,
                 "wangid":[1, 0, 1, 0, 0, 0, 1, 1]
                }, 
                {
                 "tileid":243,
                 "wangid":[1, 0, 1, 0, 0, 0, 1, 0]
                }, 
                {
                 "tileid":244,
                 "wangid":[1, 1, 1, 0, 0, 0, 1, 0]
                }, 
                {
                 "tileid":259,
                 "wangid":[1, 0, 1, 0, 1, 0, 0, 0]
                }, 
                {
                 "tileid":260,
                 "wangid":[1, 0, 0, 0, 1, 0, 1, 0]
                }, 
                {
                 "tileid":261,
                 "wangid":[0, 0, 1, 0, 1, 0, 0, 0]
                }, 
                {
                 "tileid":262,
                 "wangid":[0, 0, 0, 0, 1, 0, 1, 0]
                }, 
                {
                 "tileid":263,
                 "wangid":[1, 0, 1, 0, 1, 0, 1, 1]
                }, 
                {
                 "tileid":264,
                 "wangid":[1, 1, 1, 0, 1, 0, 1, 0]
                }, 
                {
                 "tileid":280,
                 "wangid":[1, 0, 1, 1, 1, 0, 0, 0]
                }, 
                {
                 "tileid":281,
                 "wangid":[1, 0, 0, 0, 1, 1, 1, 0]
                }, 
                {
                 "tileid":282,
                 "wangid":[1, 0, 1, 0, 0, 0, 0, 0]
                }, 
                {
                 "tileid":283,
                 "wangid":[1, 0, 0, 0, 0, 0, 1, 0]
                }, 
                {
                 "tileid":284,
                 "wangid":[1, 0, 1, 0, 1, 1, 1, 0]
                }, 
                {
                 "tileid":285,
                 "wangid":[1, 0, 1, 1, 1, 0, 1, 0]
                }]
        }, 
        {
         "colors":[
                {
                 "color":"#ff0000",
                 "name":"",
                 "probability":1,
                 "tile":227
                }],
         "name":"0_2_1",
         "tile":227,
         "type":"mixed",
         "wangtiles":[
                {
                 "tileid":161,
                 "wangid":[0, 0, 1, 1, 1, 0, 0, 0]
                }, 
                {
                 "tileid":162,
                 "wangid":[0, 0, 1, 1, 1, 1, 1, 0]
                }, 
                {
                 "tileid":163,
                 "wangid":[0, 0, 0, 0, 1, 1, 1, 0]
                }, 
                {
                 "tileid":164,
                 "wangid":[0, 0, 0, 0, 1, 0, 0, 0]
                }, 
                {
                 "tileid":165,
                 "wangid":[1, 1, 1, 0, 1, 1, 1, 1]
                }, 
                {
                 "tileid":166,
                 "wangid":[1, 1, 1, 0, 1, 0, 1, 1]
                }, 
                {
                 "tileid":167,
                 "wangid":[1, 1, 1, 1, 1, 0, 1, 1]
                }, 
                {
                 "tileid":182,
                 "wangid":[1, 1, 1, 1, 1, 0, 0, 0]
                }, 
                {
                 "tileid":183,
                 "wangid":[1, 1, 1, 1, 1, 1, 1, 1]
                }, 
                {
                 "tileid":184,
                 "wangid":[1, 0, 0, 0, 1, 1, 1, 1]
                }, 
                {
                 "tileid":185,
                 "wangid":[1, 0, 0, 0, 1, 0, 0, 0]
                }, 
                {
                 "tileid":186,
                 "wangid":[1, 0, 1, 0, 1, 1, 1, 1]
                }, 
                {
                 "tileid":187,
                 "wangid":[1, 0, 1, 0, 1, 0, 1, 0]
                }, 
                {
                 "tileid":188,
                 "wangid":[1, 1, 1, 1, 1, 0, 1, 0]
                }, 
                {
                 "tileid":203,
                 "wangid":[1, 1, 1, 0, 0, 0, 0, 0]
                }, 
                {
                 "tileid":204,
                 "wangid":[1, 1, 1, 0, 0, 0, 1, 1]
                }, 
                {
                 "tileid":205,
                 "wangid":[1, 0, 0, 0, 0, 0, 1, 1]
                }, 
                {
                 "tileid":206,
                 "wangid":[1, 0, 0, 0, 0, 0, 0, 0]
                }, 
                {
                 "tileid":207,
                 "wangid":[1, 0, 1, 1, 1, 1, 1, 1]
                }, 
                {
                 "tileid":208,
                 "wangid":[1, 0, 1, 1, 1, 1, 1, 0]
                }, 
                {
                 "tileid":209,
                 "wangid":[1, 1, 1, 1, 1, 1, 1, 0]
                }, 
                {
                 "tileid":224,
                 "wangid":[0, 0, 1, 0, 0, 0, 0, 0]
                }, 
                {
                 "tileid":225,
                 "wangid":[0, 0, 1, 0, 0, 0, 1, 0]
                }, 
                {
                 "tileid":226,
                 "wangid":[0, 0, 0, 0, 0, 0, 1, 0]
                }, 
                {
                 "tileid":228,
                 "wangid":[0, 0, 1, 0, 1, 1, 1, 0]
                }, 
                {
                 "tileid":229,
                 "wangid":[0, 0, 1, 0, 1, 0, 1, 0]
                }, 
                {
                 "tileid":230,
                 "wangid":[0, 0, 1, 1, 1, 0, 1, 0]
                }, 
                {
                 "tileid":245,
                 "wangid":[1, 1, 1, 0, 1, 0, 0, 0]
                }, 
                {
                 "tileid":246,
                 "wangid":[1, 0, 0, 0, 1, 0, 1, 1]
                }, 
                {
                 "tileid":247,
                 "wangid":[1, 1, 1, 0, 1, 1, 1, 0]
                }, 
                {
                 "tileid":248,
                 "wangid":[1, 0, 1, 1, 1, 0, 1, 1]
                }, 
                {
                 "tileid":249,
                 "wangid":[1, 0, 1, 0, 0, 0, 1, 1]
                }, 
                {
                 "tileid":250,
                 "wangid":[1, 0, 1, 0, 0, 0, 1, 0]
                }, 
                {
                 "tileid":251,
                 "wangid":[1, 1, 1, 0, 0, 0, 1, 0]
                }, 
                {
                 "tileid":266,
                 "wangid":[1, 0, 1, 0, 1, 0, 0, 0]
                }, 
                {
                 "tileid":267,
                 "wangid":[1, 0, 0, 0, 1, 0, 1, 0]
                }, 
                {
                 "tileid":268,
                 "wangid":[0, 0, 1, 0, 1, 0, 0, 0]
                }, 
                {
                 "tileid":269,
                 "wangid":[0, 0, 0, 0, 1, 0, 1, 0]
                }, 
                {
                 "tileid":270,
                 "wangid":[1, 0, 1, 0, 1, 0, 1, 1]
                }, 
                {
                 "tileid":271,
                 "wangid":[1, 1, 1, 0, 1, 0, 1, 0]
                }, 
                {
                 "tileid":287,
                 "wangid":[1, 0, 1, 1, 1, 0, 0, 0]
                }, 
                {
                 "tileid":288,
                 "wangid":[1, 0, 0, 0, 1, 1, 1, 0]
                }, 
                {
                 "tileid":289,
                 "wangid":[1, 0, 1, 0, 0, 0, 0, 0]
                }, 
                {
                 "tileid":290,
                 "wangid":[1, 0, 0, 0, 0, 0, 1, 0]
                }, 
                {
                 "tileid":291,
                 "wangid":[1, 0, 1, 0, 1, 1, 1, 0]
                }, 
                {
                 "tileid":292,
                 "wangid":[1, 0, 1, 1, 1, 0, 1, 0]
                }]
        }, 
        {
         "colors":[
                {
                 "color":"#ff0000",
                 "name":"",
                 "probability":1,
                 "tile":360
                }],
         "name":"0_0_2",
         "tile":360,
         "type":"mixed",
         "wangtiles":[
                {
                 "tileid":294,
                 "wangid":[0, 0, 1, 1, 1, 0, 0, 0]
                }, 
                {
                 "tileid":295,
                 "wangid":[0, 0, 1, 1, 1, 1, 1, 0]
                }, 
                {
                 "tileid":296,
                 "wangid":[0, 0, 0, 0, 1, 1, 1, 0]
                }, 
                {
                 "tileid":297,
                 "wangid":[0, 0, 0, 0, 1, 0, 0, 0]
                }, 
                {
                 "tileid":298,
                 "wangid":[1, 1, 1, 0, 1, 1, 1, 1]
                }, 
                {
                 "tileid":299,
                 "wangid":[1, 1, 1, 0, 1, 0, 1, 1]
                }, 
                {
                 "tileid":300,
                 "wangid":[1, 1, 1, 1, 1, 0, 1, 1]
                }, 
                {
                 "tileid":315,
                 "wangid":[1, 1, 1, 1, 1, 0, 0, 0]
                }, 
                {
                 "tileid":316,
                 "wangid":[1, 1, 1, 1, 1, 1, 1, 1]
                }, 
                {
                 "tileid":317,
                 "wangid":[1, 0, 0, 0, 1, 1, 1, 1]
                }, 
                {
                 "tileid":318,
                 "wangid":[1, 0, 0, 0, 1, 0, 0, 0]
                }, 
                {
                 "tileid":319,
                 "wangid":[1, 0, 1, 0, 1, 1, 1, 1]
                }, 
                {
                 "tileid":320,
                 "wangid":[1, 0, 1, 0, 1, 0, 1, 0]
                }, 
                {
                 "tileid":321,
                 "wangid":[1, 1, 1, 1, 1, 0, 1, 0]
                }, 
                {
                 "tileid":336,
                 "wangid":[1, 1, 1, 0, 0, 0, 0, 0]
                }, 
                {
                 "tileid":337,
                 "wangid":[1, 1, 1, 0, 0, 0, 1, 1]
                }, 
                {
                 "tileid":338,
                 "wangid":[1, 0, 0, 0, 0, 0, 1, 1]
                }, 
                {
                 "tileid":339,
                 "wangid":[1, 0, 0, 0, 0, 0, 0, 0]
                }, 
                {
                 "tileid":340,
                 "wangid":[1, 0, 1, 1, 1, 1, 1, 1]
                }, 
                {
                 "tileid":341,
                 "wangid":[1, 0, 1, 1, 1, 1, 1, 0]
                }, 
                {
                 "tileid":342,
                 "wangid":[1, 1, 1, 1, 1, 1, 1, 0]
                }, 
                {
                 "tileid":357,
                 "wangid":[0, 0, 1, 0, 0, 0, 0, 0]
                }, 
                {
                 "tileid":358,
                 "wangid":[0, 0, 1, 0, 0, 0, 1, 0]
                }, 
                {
                 "tileid":359,
                 "wangid":[0, 0, 0, 0, 0, 0, 1, 0]
                }, 
                {
                 "tileid":361,
                 "wangid":[0, 0, 1, 0, 1, 1, 1, 0]
                }, 
                {
                 "tileid":362,
                 "wangid":[0, 0, 1, 0, 1, 0, 1, 0]
                }, 
                {
                 "tileid":363,
                 "wangid":[0, 0, 1, 1, 1, 0, 1, 0]
                }, 
                {
                 "tileid":378,
                 "wangid":[1, 1, 1, 0, 1, 0, 0, 0]
                }, 
                {
                 "tileid":379,
                 "wangid":[1, 0, 0, 0, 1, 0, 1, 1]
                }, 
                {
                 "tileid":380,
                 "wangid":[1, 1, 1, 0, 1, 1, 1, 0]
                }, 
                {
                 "tileid":381,
                 "wangid":[1, 0, 1, 1, 1, 0, 1, 1]
                }, 
                {
                 "tileid":382,
                 "wangid":[1, 0, 1, 0, 0, 0, 1, 1]
                }, 
                {
                 "tileid":383,
                 "wangid":[1, 0, 1, 0, 0, 0, 1, 0]
                }, 
                {
                 "tileid":384,
                 "wangid":[1, 1, 1, 0, 0, 0, 1, 0]
                }, 
                {
                 "tileid":399,
                 "wangid":[1, 0, 1, 0, 1, 0, 0, 0]
                }, 
                {
                 "tileid":400,
                 "wangid":[1, 0, 0, 0, 1, 0, 1, 0]
                }, 
                {
                 "tileid":401,
                 "wangid":[0, 0, 1, 0, 1, 0, 0, 0]
                }, 
                {
                 "tileid":402,
                 "wangid":[0, 0, 0, 0, 1, 0, 1, 0]
                }, 
                {
                 "tileid":403,
                 "wangid":[1, 0, 1, 0, 1, 0, 1, 1]
                }, 
                {
                 "tileid":404,
                 "wangid":[1, 1, 1, 0, 1, 0, 1, 0]
                }, 
                {
                 "tileid":420,
                 "wangid":[1, 0, 1, 1, 1, 0, 0, 0]
                }, 
                {
                 "tileid":421,
                 "wangid":[1, 0, 0, 0, 1, 1, 1, 0]
                }, 
                {
                 "tileid":422,
                 "wangid":[1, 0, 1, 0, 0, 0, 0, 0]
                }, 
                {
                 "tileid":423,
                 "wangid":[1, 0, 0, 0, 0, 0, 1, 0]
                }, 
                {
                 "tileid":424,
                 "wangid":[1, 0, 1, 0, 1, 1, 1, 0]
                }, 
                {
                 "tileid":425,
                 "wangid":[1, 0, 1, 1, 1, 0, 1, 0]
                }]
        }, 
        {
         "colors":[
                {
                 "color":"#ff0000",
                 "name":"",
                 "probability":1,
                 "tile":367
                }],
         "name":"0_1_2",
         "tile":367,
         "type":"mixed",
         "wangtiles":[
                {
                 "tileid":301,
                 "wangid":[0, 0, 1, 1, 1, 0, 0, 0]
                }, 
                {
                 "tileid":302,
                 "wangid":[0, 0, 1, 1, 1, 1, 1, 0]
                }, 
                {
                 "tileid":303,
                 "wangid":[0, 0, 0, 0, 1, 1, 1, 0]
                }, 
                {
                 "tileid":304,
                 "wangid":[0, 0, 0, 0, 1, 0, 0, 0]
                }, 
                {
                 "tileid":305,
                 "wangid":[1, 1, 1, 0, 1, 1, 1, 1]
                }, 
                {
                 "tileid":306,
                 "wangid":[1, 1, 1, 0, 1, 0, 1, 1]
                }, 
                {
                 "tileid":307,
                 "wangid":[1, 1, 1, 1, 1, 0, 1, 1]
                }, 
                {
                 "tileid":322,
                 "wangid":[1, 1, 1, 1, 1, 0, 0, 0]
                }, 
                {
                 "tileid":323,
                 "wangid":[1, 1, 1, 1, 1, 1, 1, 1]
                }, 
                {
                 "tileid":324,
                 "wangid":[1, 0, 0, 0, 1, 1, 1, 1]
                }, 
                {
                 "tileid":325,
                 "wangid":[1, 0, 0, 0, 1, 0, 0, 0]
                }, 
                {
                 "tileid":326,
                 "wangid":[1, 0, 1, 0, 1, 1, 1, 1]
                }, 
                {
                 "tileid":327,
                 "wangid":[1, 0, 1, 0, 1, 0, 1, 0]
                }, 
                {
                 "tileid":328,
                 "wangid":[1, 1, 1, 1, 1, 0, 1, 0]
                }, 
                {
                 "tileid":343,
                 "wangid":[1, 1, 1, 0, 0, 0, 0, 0]
                }, 
                {
                 "tileid":344,
                 "wangid":[1, 1, 1, 0, 0, 0, 1, 1]
                }, 
                {
                 "tileid":345,
                 "wangid":[1, 0, 0, 0, 0, 0, 1, 1]
                }, 
                {
                 "tileid":346,
                 "wangid":[1, 0, 0, 0, 0, 0, 0, 0]
                }, 
                {
                 "tileid":347,
                 "wangid":[1, 0, 1, 1, 1, 1, 1, 1]
                }, 
                {
                 "tileid":348,
                 "wangid":[1, 0, 1, 1, 1, 1, 1, 0]
                }, 
                {
                 "tileid":349,
                 "wangid":[1, 1, 1, 1, 1, 1, 1, 0]
                }, 
                {
                 "tileid":364,
                 "wangid":[0, 0, 1, 0, 0, 0, 0, 0]
                }, 
                {
                 "tileid":365,
                 "wangid":[0, 0, 1, 0, 0, 0, 1, 0]
                }, 
                {
                 "tileid":366,
                 "wangid":[0, 0, 0, 0, 0, 0, 1, 0]
                }, 
                {
                 "tileid":368,
                 "wangid":[0, 0, 1, 0, 1, 1, 1, 0]
                }, 
                {
                 "tileid":369,
                 "wangid":[0, 0, 1, 0, 1, 0, 1, 0]
                }, 
                {
                 "tileid":370,
                 "wangid":[0, 0, 1, 1, 1, 0, 1, 0]
                }, 
                {
                 "tileid":385,
                 "wangid":[1, 1, 1, 0, 1, 0, 0, 0]
                }, 
                {
                 "tileid":386,
                 "wangid":[1, 0, 0, 0, 1, 0, 1, 1]
                }, 
                {
                 "tileid":387,
                 "wangid":[1, 1, 1, 0, 1, 1, 1, 0]
                }, 
                {
                 "tileid":388,
                 "wangid":[1, 0, 1, 1, 1, 0, 1, 1]
                }, 
                {
                 "tileid":389,
                 "wangid":[1, 0, 1, 0, 0, 0, 1, 1]
                }, 
                {
                 "tileid":390,
                 "wangid":[1, 0, 1, 0, 0, 0, 1, 0]
                }, 
                {
                 "tileid":391,
                 "wangid":[1, 1, 1, 0, 0, 0, 1, 0]
                }, 
                {
                 "tileid":406,
                 "wangid":[1, 0, 1, 0, 1, 0, 0, 0]
                }, 
                {
                 "tileid":407,
                 "wangid":[1, 0, 0, 0, 1, 0, 1, 0]
                }, 
                {
                 "tileid":408,
                 "wangid":[0, 0, 1, 0, 1, 0, 0, 0]
                }, 
                {
                 "tileid":409,
                 "wangid":[0, 0, 0, 0, 1, 0, 1, 0]
                }, 
                {
                 "tileid":410,
                 "wangid":[1, 0, 1, 0, 1, 0, 1, 1]
                }, 
                {
                 "tileid":411,
                 "wangid":[1, 1, 1, 0, 1, 0, 1, 0]
                }, 
                {
                 "tileid":427,
                 "wangid":[1, 0, 1, 1, 1, 0, 0, 0]
                }, 
                {
                 "tileid":428,
                 "wangid":[1, 0, 0, 0, 1, 1, 1, 0]
                }, 
                {
                 "tileid":429,
                 "wangid":[1, 0, 1, 0, 0, 0, 0, 0]
                }, 
                {
                 "tileid":430,
                 "wangid":[1, 0, 0, 0, 0, 0, 1, 0]
                }, 
                {
                 "tileid":431,
                 "wangid":[1, 0, 1, 0, 1, 1, 1, 0]
                }, 
                {
                 "tileid":432,
                 "wangid":[1, 0, 1, 1, 1, 0, 1, 0]
                }]
        }, 
        {
         "colors":[
                {
                 "color":"#ff0000",
                 "name":"",
                 "probability":1,
                 "tile":374
                }],
         "name":"0_2_2",
         "tile":374,
         "type":"mixed",
         "wangtiles":[
                {
                 "tileid":308,
                 "wangid":[0, 0, 1, 1, 1, 0, 0, 0]
                }, 
                {
                 "tileid":309,
                 "wangid":[0, 0, 1, 1, 1, 1, 1, 0]
                }, 
                {
                 "tileid":310,
                 "wangid":[0, 0, 0, 0, 1, 1, 1, 0]
                }, 
                {
                 "tileid":311,
                 "wangid":[0, 0, 0, 0, 1, 0, 0, 0]
                }, 
                {
                 "tileid":312,
                 "wangid":[1, 1, 1, 0, 1, 1, 1, 1]
                }, 
                {
                 "tileid":313,
                 "wangid":[1, 1, 1, 0, 1, 0, 1, 1]
                }, 
                {
                 "tileid":314,
                 "wangid":[1, 1, 1, 1, 1, 0, 1, 1]
                }, 
                {
                 "tileid":329,
                 "wangid":[1, 1, 1, 1, 1, 0, 0, 0]
                }, 
                {
                 "tileid":330,
                 "wangid":[1, 1, 1, 1, 1, 1, 1, 1]
                }, 
                {
                 "tileid":331,
                 "wangid":[1, 0, 0, 0, 1, 1, 1, 1]
                }, 
                {
                 "tileid":332,
                 "wangid":[1, 0, 0, 0, 1, 0, 0, 0]
                }, 
                {
                 "tileid":333,
                 "wangid":[1, 0, 1, 0, 1, 1, 1, 1]
                }, 
                {
                 "tileid":334,
                 "wangid":[1, 0, 1, 0, 1, 0, 1, 0]
                }, 
                {
                 "tileid":335,
                 "wangid":[1, 1, 1, 1, 1, 0, 1, 0]
                }, 
                {
                 "tileid":350,
                 "wangid":[1, 1, 1, 0, 0, 0, 0, 0]
                }, 
                {
                 "tileid":351,
                 "wangid":[1, 1, 1, 0, 0, 0, 1, 1]
                }, 
                {
                 "tileid":352,
                 "wangid":[1, 0, 0, 0, 0, 0, 1, 1]
                }, 
                {
                 "tileid":353,
                 "wangid":[1, 0, 0, 0, 0, 0, 0, 0]
                }, 
                {
                 "tileid":354,
                 "wangid":[1, 0, 1, 1, 1, 1, 1, 1]
                }, 
                {
                 "tileid":355,
                 "wangid":[1, 0, 1, 1, 1, 1, 1, 0]
                }, 
                {
                 "tileid":356,
                 "wangid":[1, 1, 1, 1, 1, 1, 1, 0]
                }, 
                {
                 "tileid":371,
                 "wangid":[0, 0, 1, 0, 0, 0, 0, 0]
                }, 
                {
                 "tileid":372,
                 "wangid":[0, 0, 1, 0, 0, 0, 1, 0]
                }, 
                {
                 "tileid":373,
                 "wangid":[0, 0, 0, 0, 0, 0, 1, 0]
                }, 
                {
                 "tileid":375,
                 "wangid":[0, 0, 1, 0, 1, 1, 1, 0]
                }, 
                {
                 "tileid":376,
                 "wangid":[0, 0, 1, 0, 1, 0, 1, 0]
                }, 
                {
                 "tileid":377,
                 "wangid":[0, 0, 1, 1, 1, 0, 1, 0]
                }, 
                {
                 "tileid":392,
                 "wangid":[1, 1, 1, 0, 1, 0, 0, 0]
                }, 
                {
                 "tileid":393,
                 "wangid":[1, 0, 0, 0, 1, 0, 1, 1]
                }, 
                {
                 "tileid":394,
                 "wangid":[1, 1, 1, 0, 1, 1, 1, 0]
                }, 
                {
                 "tileid":395,
                 "wangid":[1, 0, 1, 1, 1, 0, 1, 1]
                }, 
                {
                 "tileid":396,
                 "wangid":[1, 0, 1, 0, 0, 0, 1, 1]
                }, 
                {
                 "tileid":397,
                 "wangid":[1, 0, 1, 0, 0, 0, 1, 0]
                }, 
                {
                 "tileid":398,
                 "wangid":[1, 1, 1, 0, 0, 0, 1, 0]
                }, 
                {
                 "tileid":413,
                 "wangid":[1, 0, 1, 0, 1, 0, 0, 0]
                }, 
                {
                 "tileid":414,
                 "wangid":[1, 0, 0, 0, 1, 0, 1, 0]
                }, 
                {
                 "tileid":415,
                 "wangid":[0, 0, 1, 0, 1, 0, 0, 0]
                }, 
                {
                 "tileid":416,
                 "wangid":[0, 0, 0, 0, 1, 0, 1, 0]
                }, 
                {
                 "tileid":417,
                 "wangid":[1, 0, 1, 0, 1, 0, 1, 1]
                }, 
                {
                 "tileid":418,
                 "wangid":[1, 1, 1, 0, 1, 0, 1, 0]
                }, 
                {
                 "tileid":434,
                 "wangid":[1, 0, 1, 1, 1, 0, 0, 0]
                }, 
                {
                 "tileid":435,
                 "wangid":[1, 0, 0, 0, 1, 1, 1, 0]
                }, 
                {
                 "tileid":436,
                 "wangid":[1, 0, 1, 0, 0, 0, 0, 0]
                }, 
                {
                 "tileid":437,
                 "wangid":[1, 0, 0, 0, 0, 0, 1, 0]
                }, 
                {
                 "tileid":438,
                 "wangid":[1, 0, 1, 0, 1, 1, 1, 0]
                }, 
                {
                 "tileid":439,
                 "wangid":[1, 0, 1, 1, 1, 0, 1, 0]
                }]
        }]
}